dust/__init__.py
dust/entity.py
dust/events.py
dust/messages.py
dust/slack.py
dust/templates.py
dust/datacube/__init__.py
dust/datacube/chartui.py
dust/datacube/datacube.py
dust/httpservices/__init__.py
dust/httpservices/actioncontroller.py
dust/httpservices/commandhandler.py
dust/httpservices/servicebase.py
dust/persist/__init__.py
dust/persist/mysqlpersist.py
dust/persist/sqlpersist.py
pydust-0.1.6.dist-info/licenses/LICENSE
test/fix_dbdump.py
test/test.py
pydust-0.1.6.dist-info/METADATA
pydust-0.1.6.dist-info/WHEEL
pydust-0.1.6.dist-info/top_level.txt
pydust-0.1.6.dist-info/RECORD
