Metadata-Version: 2.4
Name: pydust
Version: 0.1.6
Summary: A lightweight dependency-aware plugin framework for Python
Author-email: Zsolt Horváth <zsolte@gmail.com>
License:                                  Apache License
Project-URL: Homepage, https://github.com/MondoAurora/pydust
Requires-Python: >=3.11
License-File: LICENSE
Requires-Dist: pytz
Requires-Dist: python-dateutil
Requires-Dist: pyyaml
Requires-Dist: jinja2
Requires-Dist: requests
Requires-Dist: mysql-connector-python
Requires-Dist: deepdiff
Dynamic: license-file
